mdtooltipslink.py
md_tooltips_link-0.2.4.dist-info/METADATA
md_tooltips_link-0.2.4.dist-info/WHEEL
md_tooltips_link-0.2.4.dist-info/top_level.txt
md_tooltips_link-0.2.4.dist-info/RECORD
