Metadata-Version: 2.1
Name: md-tooltips-link
Version: 0.2.4
Summary: A Python markdown extension for implementing a glossary with tooltips
Home-page: https://github.com/mattpitkin/md-tooltips-link
Maintainer: Matt Pitkin
Maintainer-email: matthew.pitkin@ligo.org
Requires-Dist: markdown >=2.5
Requires-Dist: requests
